framing/__init__.py
framing/__main__.py
framing/backends.py
framing/base.py
framing/codecs.py
framing/command.py
framing/data_queue.py
framing/fields.py
framing/frame_processors.py
framing/frames.py
framing/layer_stack.py
framing/raw_data.py
framing/frame_types/__init__.py
framing/frame_types/dhcp_frames.py
framing/frame_types/dns_frames.py
framing/frame_types/ethernet_frames.py
framing/frame_types/ip_utilities.py
framing/frame_types/ipv4_frames.py
framing/frame_types/ipv6_frames.py
framing/frame_types/pcap_frames.py
framing/frame_types/tcp_frames.py
framing/frame_types/tls_frames.py
framing/frame_types/udp_frames.py
packet_framing-0.2.1.dist-info/LICENSE
packet_framing-0.2.1.dist-info/METADATA
packet_framing-0.2.1.dist-info/WHEEL
packet_framing-0.2.1.dist-info/top_level.txt
packet_framing-0.2.1.dist-info/RECORD
