Metadata-Version: 2.1
Name: packet-framing
Version: 0.2.1
Summary: Protocol packet parsing tool
Home-page: https://gitlab.com/CinCan/framing
Author: Rauli Kaksonen
Author-email: rauli.kaksonen@gmail.com
Classifier: Programming Language :: Python :: 3
Classifier: Operating System :: OS Independent
Requires-Python: >=3.8
License-File: LICENSE
Requires-Dist: PyYAML
